sso_config_generator/__init__.py
sso_config_generator/cli.py
sso_config_generator/core.py
sso_config_generator/version.py
sso_config_generator-1.4.1.dist-info/licenses/LICENSE
sso_config_generator-1.4.1.dist-info/METADATA
sso_config_generator-1.4.1.dist-info/WHEEL
sso_config_generator-1.4.1.dist-info/entry_points.txt
sso_config_generator-1.4.1.dist-info/top_level.txt
sso_config_generator-1.4.1.dist-info/RECORD
