Metadata-Version: 2.4
Name: sso-config-generator
Version: 1.4.1
Summary: Python tool for generating AWS SSO configuration and directory structure
Author-email: easytocloud <info@easytocloud.com>
License: MIT License
Project-URL: Homepage, https://github.com/easytocloud/sso-config-generator
Project-URL: Repository, https://github.com/easytocloud/sso-config-generator
Project-URL: Issues, https://github.com/easytocloud/sso-config-generator/issues
Project-URL: Changelog, https://github.com/easytocloud/sso-config-generator/blob/main/CHANGELOG.md
Keywords: aws,sso,config,generator,cli,aws-cli
Classifier: Development Status :: 4 - Beta
Classifier: Environment :: Console
Classifier: Intended Audience :: Developers
Classifier: License :: OSI Approved :: MIT License
Classifier: Operating System :: OS Independent
Classifier: Programming Language :: Python :: 3
Classifier: Programming Language :: Python :: 3.8
Classifier: Programming Language :: Python :: 3.9
Classifier: Programming Language :: Python :: 3.10
Classifier: Programming Language :: Python :: 3.11
Classifier: Topic :: Software Development :: Build Tools
Classifier: Topic :: System :: Systems Administration
Requires-Python: >=3.8
License-File: LICENSE
Requires-Dist: boto3>=1.34.0
Requires-Dist: click>=8.1.0
Requires-Dist: pyyaml>=6.0.1
Dynamic: license-file
